mybase_mcp_server/__init__.py
mybase_mcp_server/server.py
mybase_mcp_server-0.1.0.dist-info/METADATA
mybase_mcp_server-0.1.0.dist-info/WHEEL
mybase_mcp_server-0.1.0.dist-info/entry_points.txt
mybase_mcp_server-0.1.0.dist-info/RECORD
