Metadata-Version: 2.4
Name: mybase-mcp-server
Version: 0.1.0
Summary: A MCP server project
Author-email: 血剑 <mengjie.jmj@alibaba-inc.com>
Requires-Python: >=3.13
Requires-Dist: mcp>=1.9.4
